personnummer/__init__.py
personnummer/main.py
personnummer/personnummer.py
personnummer/tests/__init__.py
personnummer/tests/test_personnummer.py
personnummer-3.2.1.dist-info/LICENSE
personnummer-3.2.1.dist-info/METADATA
personnummer-3.2.1.dist-info/WHEEL
personnummer-3.2.1.dist-info/entry_points.txt
personnummer-3.2.1.dist-info/top_level.txt
personnummer-3.2.1.dist-info/RECORD
