Metadata-Version: 2.1
Name: personnummer
Version: 3.2.1
Summary: Validate Swedish personal identity numbers
Author-email: Personnummer and Contributors <hello@personnummer.dev>
License: MIT License
Project-URL: Homepage, https://personnummer.dev
Project-URL: Repository, https://github.com/personnummer/python
Classifier: License :: OSI Approved :: MIT License
License-File: LICENSE
Provides-Extra: dev
Requires-Dist: pytest ; extra == 'dev'
Requires-Dist: build ; extra == 'dev'
